{"bomFormat":"CycloneDX","metadata":{"timestamp":"2024-01-15T03:52:22"},"serialNumber":"urn:uuid:8a95988a-c894-44f6-ad72-00bd826cd713","components":[{"version":"240115.12025","type":"application","name":"luci-app-homeproxy"},{"name":"luci-app-ipinfo","type":"application","version":"2.0.1"},{"name":"luci-app-openclash","version":"0.45.157-beta","type":"application"},{"name":"luci-app-passwall","version":"4.72","type":"application"},{"version":"240115.12025","type":"application","name":"luci-i18n-homeproxy-zh-cn"},{"name":"luci-i18n-passwall-zh-cn","type":"application","version":"240115.12025"},{"version":"3.9.1-beta","type":"application","name":"luci-theme-alpha"}],"version":1,"specVersion":"1.4"}