{"components":[{"version":"20230311","type":"application","name":"ca-bundle"},{"version":"20230311","name":"ca-certificates","type":"application"},{"version":"2023-05-23-75a3b870","name":"jshn","type":"application","licenses":[{"license":{"name":"ISC"}}]},{"licenses":[{"license":{"name":"ISC"}}],"type":"library","name":"libblobmsg-json20230523","version":"2023-05-23-75a3b870"},{"name":"libjson-c5","type":"library","cpe":"cpe:/a:json-c_project:json-c:0.16","version":"0.16","licenses":[{"license":{"name":"MIT"}}]},{"licenses":[{"license":{"name":"ISC"}}],"version":"2023-05-23-75a3b870","name":"libjson-script20230523","type":"application"},{"version":"5.1.5","type":"library","cpe":"cpe:/a:lua:lua:5.1.5","name":"liblua5.1.5","licenses":[{"license":{"name":"MIT"}}]},{"version":"2.28.5","type":"library","cpe":"cpe:/a:arm:mbed_tls:2.28.5","name":"libmbedtls12","licenses":[{"license":{"name":"GPL-2.0-or-later"}}]},{"version":"2023-05-23-75a3b870","name":"libubox-lua","type":"library","licenses":[{"license":{"name":"ISC"}}]},{"version":"2023-05-23-75a3b870","name":"libubox20230523","type":"library","licenses":[{"license":{"name":"ISC"}}]},{"licenses":[{"license":{"name":"MIT"}}],"version":"5.1.5","type":"application","cpe":"cpe:/a:lua:lua:5.1.5","name":"lua"},{"name":"lua-examples","type":"application","cpe":"cpe:/a:lua:lua:5.1.5","version":"5.1.5","licenses":[{"license":{"name":"MIT"}}]},{"version":"5.1.5","type":"application","cpe":"cpe:/a:lua:lua:5.1.5","name":"luac","licenses":[{"license":{"name":"MIT"}}]},{"licenses":[{"license":{"name":"GPL-2.0-or-later"}}],"cpe":"cpe:/a:arm:mbed_tls:2.28.5","type":"application","name":"mbedtls-util","version":"2.28.5"},{"version":"2020-05-23-f1f65026","name":"usign","type":"application","licenses":[{"license":{"name":"ISC"}}]}],"metadata":{"timestamp":"2024-01-14T04:24:22"},"serialNumber":"urn:uuid:c3466c47-1fc8-4ced-b059-c75672046e59","specVersion":"1.4","bomFormat":"CycloneDX","version":1}