{"version":1,"components":[{"cpe":"cpe:/a:haxx:libcurl:8.4.0","version":"8.4.0","type":"application","licenses":[{"license":{"name":"MIT"}}],"name":"curl"},{"cpe":"cpe:/a:haxx:libcurl:8.4.0","version":"8.4.0","type":"library","name":"libcurl4","licenses":[{"license":{"name":"MIT"}}]},{"licenses":[{"license":{"name":"MIT"}}],"name":"libnghttp2-14","type":"library","version":"1.57.0"}],"specVersion":"1.4","metadata":{"timestamp":"2024-01-14T04:24:19"},"serialNumber":"urn:uuid:d1a3276f-f0d1-4640-978b-9247f66e18e4","bomFormat":"CycloneDX"}